pyrex/__init__.py
pyrex/email.py
pyrex_lib-0.1.0.dist-info/DESCRIPTION.rst
pyrex_lib-0.1.0.dist-info/METADATA
pyrex_lib-0.1.0.dist-info/RECORD
pyrex_lib-0.1.0.dist-info/WHEEL
pyrex_lib-0.1.0.dist-info/metadata.json
pyrex_lib-0.1.0.dist-info/pbr.json
pyrex_lib-0.1.0.dist-info/top_level.txt
