Metadata-Version: 2.0
Name: pyrex-lib
Version: 0.1.0
Summary: A minimalist library for performing string validation in Python, powered by regular expressions.
Home-page: https://github.com/jacobsimon/pyrex
Author: Jacob Simon
Author-email: jacob.anthony.simon@gmail.com
License: MIT
Keywords: validation regex testing development
Platform: UNKNOWN
Classifier: Intended Audience :: Developers
Classifier: License :: OSI Approved :: MIT License
Classifier: Programming Language :: Python :: 2.7
Classifier: Programming Language :: Python :: 3
Classifier: Programming Language :: Python :: 3.3
Classifier: Programming Language :: Python :: 3.4
Classifier: Programming Language :: Python :: 3.5
